fletx/__init__.py
fletx/view_internal_error.py
fletx/view_not_found.py
fletx/xapp.py
fletx/xmiddleware.py
fletx/xparams.py
fletx/xstate.py
fletx/xview.py
fletx/controls/__init__.py
fletx/controls/is_loading.py
fletx/controls/switch.py
fletx-0.2.0.dist-info/LICENSE
fletx-0.2.0.dist-info/METADATA
fletx-0.2.0.dist-info/WHEEL
fletx-0.2.0.dist-info/top_level.txt
fletx-0.2.0.dist-info/RECORD
