Metadata-Version: 2.1
Name: fletx
Version: 0.2.0
Summary: FletX is a powerful routing and state management library for the Flet framework. It simplifies application development by separating UI and logic while providing intuitive navigation solutions.
Home-page: https://github.com/saurabhwadekar/FletX
Author: Saurabh Wadekar [ INDIA ]
Maintainer: Saurabh Wadekar
Maintainer-email: saurabhwadekar420@gmail.com
License: MIT
Keywords: flet,routing,fletx,routes,state,flet app
License-File: LICENSE
Requires-Dist: repath
Requires-Dist: flet
